[
  {
    "name": "jsonforms-designer",
    "desc": "Visual form designer for JSONForms — optimized for government/civic forms",
    "lang": "TypeScript",
    "langColor": "#4f9cf9",
    "url": "https://github.com/TheMightyNighty/jsonforms-designer",
    "ogUrl": null,
    "stars": 0,
    "forks": 0,
    "updatedAt": "2026-06-22T05:12:56Z"
  },
  {
    "name": "ImpExpNL",
    "desc": "Modernisierte Export Import Extension für Typo3",
    "lang": "PHP",
    "langColor": "#a78bfa",
    "url": "https://github.com/TheMightyNighty/ImpExpNL",
    "ogUrl": "./screenshots/ImpExpNL.png",
    "stars": 0,
    "forks": 0,
    "updatedAt": "2026-06-21T18:34:32Z"
  },
  {
    "name": "SightMetrics",
    "desc": "Performance & Visibility Monitoring Dashboard",
    "lang": "Shell",
    "langColor": "#89e051",
    "url": "https://github.com/TheMightyNighty/SightMetrics",
    "ogUrl": "./screenshots/SightMetrics.png",
    "stars": 1,
    "forks": 0,
    "updatedAt": "2026-06-26T08:18:00Z"
  }
]
